circuitpython_jepler_udecimal-1.0.12.dist-info/licenses/LICENSE
jepler_udecimal/__init__.py
jepler_udecimal/test.py
jepler_udecimal/utrig.py
circuitpython_jepler_udecimal-1.0.12.dist-info/METADATA
circuitpython_jepler_udecimal-1.0.12.dist-info/WHEEL
circuitpython_jepler_udecimal-1.0.12.dist-info/top_level.txt
circuitpython_jepler_udecimal-1.0.12.dist-info/RECORD
