Metadata-Version: 2.4
Name: circuitpython-jepler-udecimal
Version: 1.0.12
Summary: Reduced version of the decimal library for CircuitPython
Author-email: Jeff Epler <jepler@gmail.com>
License: MIT
Project-URL: Source, https://github.com/jepler/Jepler_CircuitPython_udecimal
Project-URL: Documentation, https://jepler-udecimal.readthedocs.io/en/latest/api/jepler_udecimal/index.html
Project-URL: Tracker, https://github.com/jepler/Jepler_CircuitPython_udecimal/issues
Keywords: adafruit,blinka,circuitpython,micropython,udecimal,numeric,helper,arbitraryprecision,math
Classifier: Intended Audience :: Developers
Classifier: Topic :: Software Development :: Libraries
Classifier: Topic :: Software Development :: Embedded Systems
Classifier: Topic :: System :: Hardware
Classifier: License :: OSI Approved :: MIT License
Classifier: License :: OSI Approved :: Python Software Foundation License
Classifier: Programming Language :: Python :: 3
License-File: LICENSE
Dynamic: license-file
